MANIFEST.in
README.md
setup.cfg
setup.py
tvdosage/__init__.py
tvdosage/dosagedaemon.py
tvdosage/logmanager.py
tvdosage/models.py
tvdosage/tvdosage.py
tvdosage.egg-info/PKG-INFO
tvdosage.egg-info/SOURCES.txt
tvdosage.egg-info/dependency_links.txt
tvdosage.egg-info/entry_points.txt
tvdosage.egg-info/requires.txt
tvdosage.egg-info/top_level.txt