Metadata-Version: 1.1
Name: tvdosage
Version: 0.1.3
Summary: Keep your Tv Series dose going
Home-page: http://github.com/jairot/dosage/
Author: Jairo Trad
Author-email: jtrad@insus.com.ar
License: MIT
Platform: UNKNOWN
Classifier: Development Status :: 2 - Pre-Alpha
Classifier: Intended Audience :: End Users/Desktop
Classifier: Natural Language :: English
Classifier: License :: OSI Approved :: MIT License
Classifier: Operating System :: OS Independent
Classifier: Programming Language :: Python
Classifier: Programming Language :: Python :: 2.7
